LICENCE.txt
MANIFEST.in
README.rst
setup.cfg
setup.py
Optimus.egg-info/PKG-INFO
Optimus.egg-info/SOURCES.txt
Optimus.egg-info/dependency_links.txt
Optimus.egg-info/entry_points.txt
Optimus.egg-info/requires.txt
Optimus.egg-info/top_level.txt
Optimus.egg-info/zip-safe
optimus/__init__.py
optimus/exceptions.py
optimus/logs.py
optimus/setup_project.py
optimus/assets/__init__.py
optimus/assets/rcssmin_webassets_filter.py
optimus/assets/registry.py
optimus/cli/__init__.py
optimus/cli/build.py
optimus/cli/console_script.py
optimus/cli/po.py
optimus/cli/runserver.py
optimus/cli/startproject.py
optimus/cli/version.py
optimus/cli/watch.py
optimus/conf/__init__.py
optimus/conf/loader.py
optimus/conf/model.py
optimus/conf/registry.py
optimus/i18n/__init__.py
optimus/i18n/lang.py
optimus/i18n/manager.py
optimus/interfaces/__init__.py
optimus/interfaces/build.py
optimus/interfaces/po.py
optimus/interfaces/runserver.py
optimus/interfaces/starter.py
optimus/interfaces/watch.py
optimus/pages/__init__.py
optimus/pages/builder.py
optimus/pages/registry.py
optimus/pages/views/__init__.py
optimus/pages/views/base.py
optimus/pages/views/template.py
optimus/starters/__init__.py
optimus/utils/__init__.py
optimus/utils/assets.py
optimus/utils/cleaning_system.py
optimus/utils/directory.py
optimus/utils/jsons.py
optimus/utils/server.py
optimus/utils/settings.py
optimus/watchers/__init__.py
optimus/watchers/assets.py
optimus/watchers/datas.py
optimus/watchers/templates.py